[
  {
    "id" : "a12f5311-8046-4ceb-b94c-9ed52584fa1d",
    "prId" : 982,
    "comments" : [
      {
        "id" : "49fc5d6b-a234-4aa0-816e-de15286485a4",
        "parentId" : null,
        "author" : {
          "login" : "olafurpg",
          "name" : "Ólafur Páll Geirsson",
          "avatarUrl" : "https://avatars0.githubusercontent.com/u/1408093?v=4"
        },
        "body" : "Should this change be included?",
        "createdAt" : "2019-10-16T08:48:13Z",
        "updatedAt" : "2019-10-17T09:27:10Z",
        "lastEditedBy" : {
          "login" : "olafurpg",
          "name" : "Ólafur Páll Geirsson",
          "avatarUrl" : "https://avatars0.githubusercontent.com/u/1408093?v=4"
        },
        "tags" : [
        ]
      },
      {
        "id" : "c5be5a8b-d0ec-4413-a1a9-557c9b133330",
        "parentId" : "49fc5d6b-a234-4aa0-816e-de15286485a4",
        "author" : {
          "login" : "tgodzik",
          "name" : "Tomasz Godzik",
          "avatarUrl" : "https://avatars0.githubusercontent.com/u/3807253?u=094831e6a696f583ddfd86d3e5923fd8545c543a&v=4"
        },
        "body" : "That's fine, we want to have it gitignored",
        "createdAt" : "2019-10-16T11:04:52Z",
        "updatedAt" : "2019-10-17T09:27:10Z",
        "lastEditedBy" : {
          "login" : "tgodzik",
          "name" : "Tomasz Godzik",
          "avatarUrl" : "https://avatars0.githubusercontent.com/u/3807253?u=094831e6a696f583ddfd86d3e5923fd8545c543a&v=4"
        },
        "tags" : [
        ]
      }
    ],
    "commit" : "57ca1f238447b6283e6bbedd3d5f0eb71b45a183",
    "line" : 8,
    "diffHunk" : "@@ -1,1 +45,49 @@!website/i18n/en.json\n\nproject/metals.sbt"
  }
]