[
  {
    "id" : "4eeebc3b-4d1b-4cf4-8adf-485e43957b03",
    "prId" : 2055,
    "comments" : [
      {
        "id" : "802e3437-881e-4af4-aaa5-88228809e48c",
        "parentId" : null,
        "author" : {
          "login" : "ckipp01",
          "name" : "Chris Kipp",
          "avatarUrl" : "https://avatars0.githubusercontent.com/u/13974112?u=7b6a2ddab8eec6f99e4e40ae9b81f71cb5ba92e5&v=4"
        },
        "body" : "Super nitpicky, but we had different types of icons, and this aligns them to all be the same 游땳 ",
        "createdAt" : "2020-09-07T08:37:03Z",
        "updatedAt" : "2020-09-07T08:37:03Z",
        "lastEditedBy" : {
          "login" : "ckipp01",
          "name" : "Chris Kipp",
          "avatarUrl" : "https://avatars0.githubusercontent.com/u/13974112?u=7b6a2ddab8eec6f99e4e40ae9b81f71cb5ba92e5&v=4"
        },
        "tags" : [
        ]
      }
    ],
    "commit" : "f002a8fc4fb229add86f71dbb27d249d79640b6d",
    "line" : 7,
    "diffHunk" : "@@ -1,1 +5,9 @@</a>\n<a href=\"https://twitter.com/scalameta\">\n<img alt=\"Follow scalameta on Twitter\" src=\"https://img.shields.io/twitter/follow/scalameta.svg?logo=twitter&color=blue\" />\n</a>\n<a href=\"https://index.scala-lang.org/scalameta/metals/metals\">"
  },
  {
    "id" : "c2710335-28a0-412e-acbe-b0fecf07df64",
    "prId" : 214,
    "comments" : [
      {
        "id" : "90f46d0a-abdd-45da-aa63-2b39c47ece28",
        "parentId" : null,
        "author" : {
          "login" : "laughedelic",
          "name" : "Alexey Alekhin",
          "avatarUrl" : "https://avatars2.githubusercontent.com/u/766656?v=4"
        },
        "body" : "I'm OK with moving away the roadmap, but I think readme should at least link to it.",
        "createdAt" : "2018-03-31T14:31:07Z",
        "updatedAt" : "2018-03-31T22:01:15Z",
        "lastEditedBy" : {
          "login" : "laughedelic",
          "name" : "Alexey Alekhin",
          "avatarUrl" : "https://avatars2.githubusercontent.com/u/766656?v=4"
        },
        "tags" : [
        ]
      },
      {
        "id" : "af133b6e-1319-4cae-98a2-16b345b35ed7",
        "parentId" : "90f46d0a-abdd-45da-aa63-2b39c47ece28",
        "author" : {
          "login" : "olafurpg",
          "name" : "칍lafur P치ll Geirsson",
          "avatarUrl" : "https://avatars0.githubusercontent.com/u/1408093?v=4"
        },
        "body" : "Done",
        "createdAt" : "2018-03-31T15:40:22Z",
        "updatedAt" : "2018-03-31T22:01:15Z",
        "lastEditedBy" : {
          "login" : "olafurpg",
          "name" : "칍lafur P치ll Geirsson",
          "avatarUrl" : "https://avatars0.githubusercontent.com/u/1408093?v=4"
        },
        "tags" : [
        ]
      }
    ],
    "commit" : "d3146fa5e1de6aea4434fb7ac94da886a8657feb",
    "line" : 33,
    "diffHunk" : "@@ -1,1 +18,22 @@* robust navigation (goto definition anywhere)\n* fast completions\n* low CPU and memory usage\n* refactoring (rename, organize imports, move class, insert type annotation)\n"
  },
  {
    "id" : "511ac5e8-01be-4f70-b03e-aaf3c9386ab7",
    "prId" : 207,
    "comments" : [
      {
        "id" : "658f5f04-251d-4305-823f-0d6cd2382da8",
        "parentId" : null,
        "author" : {
          "login" : "olafurpg",
          "name" : "칍lafur P치ll Geirsson",
          "avatarUrl" : "https://avatars0.githubusercontent.com/u/1408093?v=4"
        },
        "body" : "strictly speaking we don't use scalafix for rename because it's such a simple text edit",
        "createdAt" : "2018-03-23T23:28:42Z",
        "updatedAt" : "2018-03-23T23:30:09Z",
        "lastEditedBy" : {
          "login" : "olafurpg",
          "name" : "칍lafur P치ll Geirsson",
          "avatarUrl" : "https://avatars0.githubusercontent.com/u/1408093?v=4"
        },
        "tags" : [
        ]
      }
    ],
    "commit" : "5c3682099146050081a2e3e206fc0c57cd20dae2",
    "line" : 14,
    "diffHunk" : "@@ -1,1 +37,41 @@  - [ ] Quick-fix inspections (`textDocument/codeAction`)\n    + [x] Remove unused imports\n  - [x] Rename local symbol (`textDocument/rename`)\n  - [ ] Rename global symbol (`textDocument/rename`)\n* Formatting with Scalafmt:"
  },
  {
    "id" : "8feed910-e6b7-4c8c-ac3c-ea66fecd46bb",
    "prId" : 207,
    "comments" : [
      {
        "id" : "7d4e094a-6f98-46cf-ace7-b2a9c386c387",
        "parentId" : null,
        "author" : {
          "login" : "olafurpg",
          "name" : "칍lafur P치ll Geirsson",
          "avatarUrl" : "https://avatars0.githubusercontent.com/u/1408093?v=4"
        },
        "body" : "游녨 ",
        "createdAt" : "2018-03-23T23:28:47Z",
        "updatedAt" : "2018-03-23T23:30:09Z",
        "lastEditedBy" : {
          "login" : "olafurpg",
          "name" : "칍lafur P치ll Geirsson",
          "avatarUrl" : "https://avatars0.githubusercontent.com/u/1408093?v=4"
        },
        "tags" : [
        ]
      }
    ],
    "commit" : "5c3682099146050081a2e3e206fc0c57cd20dae2",
    "line" : 19,
    "diffHunk" : "@@ -1,1 +42,46 @@  - [x] Whole file (`textDocument/formatting`)\n  - [ ] Selected range (`textDocument/rangeFormatting`)\n  - [x] On save (`textDocument/willSaveWaitUntil`)\n  - [ ] As you type (`textDocument/onTypeFormatting`)\n* Code assistance:"
  },
  {
    "id" : "8d27aac4-1493-4db7-acec-b9d5cef96b39",
    "prId" : 95,
    "comments" : [
      {
        "id" : "c9f987ec-974c-4dd1-9d8b-40ca7dce4d36",
        "parentId" : null,
        "author" : {
          "login" : "olafurpg",
          "name" : "칍lafur P치ll Geirsson",
          "avatarUrl" : "https://avatars0.githubusercontent.com/u/1408093?v=4"
        },
        "body" : "I agree \"intellisense\" is maybe too microsoft specific, but they use it as a general term for exactly these features \r\n\r\n> IntelliSense is the general term for a number of features: List Members, Parameter Info, Quick Info, and Complete Word. These features help you to learn more about the code you are using, keep track of the parameters you are typing, and add calls to properties and methods with only a few keystrokes.\r\n",
        "createdAt" : "2017-12-06T08:46:31Z",
        "updatedAt" : "2017-12-06T08:51:24Z",
        "lastEditedBy" : {
          "login" : "olafurpg",
          "name" : "칍lafur P치ll Geirsson",
          "avatarUrl" : "https://avatars0.githubusercontent.com/u/1408093?v=4"
        },
        "tags" : [
        ]
      },
      {
        "id" : "811ad035-1615-457f-a374-0b5b06af5ad0",
        "parentId" : "c9f987ec-974c-4dd1-9d8b-40ca7dce4d36",
        "author" : {
          "login" : "laughedelic",
          "name" : "Alexey Alekhin",
          "avatarUrl" : "https://avatars2.githubusercontent.com/u/766656?v=4"
        },
        "body" : "I see your point about multiple connotations, but I'm not sure whether it's a commonly understandable term. I had a general idea when I saw this word before, but when you mentioned it yesterday I had to google the exact meaning because I wasn't sure. Probably it's just me 游땐 ",
        "createdAt" : "2017-12-06T11:51:26Z",
        "updatedAt" : "2017-12-06T11:51:26Z",
        "lastEditedBy" : {
          "login" : "laughedelic",
          "name" : "Alexey Alekhin",
          "avatarUrl" : "https://avatars2.githubusercontent.com/u/766656?v=4"
        },
        "tags" : [
        ]
      }
    ],
    "commit" : "2b8a6231c02a9df92c5fb8066bd217254209bb47",
    "line" : 27,
    "diffHunk" : "@@ -1,1 +30,34 @@  - [ ] Selected range (`textDocument/rangeFormatting`)\n  - [ ] As you type (`textDocument/onTypeFormatting`)\n* Context-aware code completion:\n  - [x] Autocompletion as you type (`textDocument/completions`)\n  - [x] Show parameter list as you type (`textDocument/signatureHelp`)"
  }
]