[
  {
    "id" : "3a6d9510-35f5-45ff-987d-0e4931cbd245",
    "prId" : 1596,
    "comments" : [
      {
        "id" : "45f14cb2-f829-4cdd-ac67-e512c1992781",
        "parentId" : null,
        "author" : {
          "login" : "gabro",
          "name" : "Gabriele Petronella",
          "avatarUrl" : "https://avatars0.githubusercontent.com/u/691940?u=5aaf176f5da60764f857b8f8c6842217f737627f&v=4"
        },
        "body" : "Out of sheer curiosity: why not markdown?",
        "createdAt" : "2020-04-09T17:59:38Z",
        "updatedAt" : "2020-04-10T11:24:09Z",
        "lastEditedBy" : {
          "login" : "gabro",
          "name" : "Gabriele Petronella",
          "avatarUrl" : "https://avatars0.githubusercontent.com/u/691940?u=5aaf176f5da60764f857b8f8c6842217f737627f&v=4"
        },
        "tags" : [
        ]
      },
      {
        "id" : "00099c23-7be8-4437-b5fa-a699f9f8634e",
        "parentId" : "45f14cb2-f829-4cdd-ac67-e512c1992781",
        "author" : {
          "login" : "tgodzik",
          "name" : "Tomasz Godzik",
          "avatarUrl" : "https://avatars0.githubusercontent.com/u/3807253?u=094831e6a696f583ddfd86d3e5923fd8545c543a&v=4"
        },
        "body" : "I can't remember exactly, but I think it's because Markdown requires column labels, we could do something like:\r\n\r\n| Summary                    |     |\r\n| -------------------------- | --- |\r\n| Commits since last release | 174 |\r\n| Merged PRs                 | 55  |\r\n| Contributors               | 9   |\r\n| Closed issues              | 13  |\r\n| New features               | 3   |\r\n\r\nbut not:\r\n\r\n| Commits since last release | 174 |\r\n| Merged PRs                 | 55  |\r\n| Contributors               | 9   |\r\n| Closed issues              | 13  |\r\n| New features               | 3   |",
        "createdAt" : "2020-04-10T14:19:49Z",
        "updatedAt" : "2020-04-10T14:19:49Z",
        "lastEditedBy" : {
          "login" : "tgodzik",
          "name" : "Tomasz Godzik",
          "avatarUrl" : "https://avatars0.githubusercontent.com/u/3807253?u=094831e6a696f583ddfd86d3e5923fd8545c543a&v=4"
        },
        "tags" : [
        ]
      },
      {
        "id" : "87255508-ed70-42b7-8ac3-0cc5d739de78",
        "parentId" : "45f14cb2-f829-4cdd-ac67-e512c1992781",
        "author" : {
          "login" : "gabro",
          "name" : "Gabriele Petronella",
          "avatarUrl" : "https://avatars0.githubusercontent.com/u/691940?u=5aaf176f5da60764f857b8f8c6842217f737627f&v=4"
        },
        "body" : "ah, that makes sense, thanks",
        "createdAt" : "2020-04-10T15:59:24Z",
        "updatedAt" : "2020-04-10T15:59:24Z",
        "lastEditedBy" : {
          "login" : "gabro",
          "name" : "Gabriele Petronella",
          "avatarUrl" : "https://avatars0.githubusercontent.com/u/691940?u=5aaf176f5da60764f857b8f8c6842217f737627f&v=4"
        },
        "tags" : [
        ]
      }
    ],
    "commit" : "98216b111b90200af63cab4201335bfed979a303",
    "line" : 11,
    "diffHunk" : "@@ -1,1 +9,13 @@the last 0.8.x version.\n\n<table>\n<tbody>\n  <tr>"
  },
  {
    "id" : "1105171b-7c60-4fe4-96fd-8c6adcc3b3e0",
    "prId" : 1596,
    "comments" : [
      {
        "id" : "f5257cc2-2a1b-4741-9b01-f8e4ea31d47f",
        "parentId" : null,
        "author" : {
          "login" : "ckipp01",
          "name" : "Chris Kipp",
          "avatarUrl" : "https://avatars0.githubusercontent.com/u/13974112?u=7b6a2ddab8eec6f99e4e40ae9b81f71cb5ba92e5&v=4"
        },
        "body" : "Is it maybe also worth putting in a reminder that in order for these the work, ensure you have code lenses enabled in your client? I'm not sure if they are for vscode, but for example they aren't be default in coc.nvim.",
        "createdAt" : "2020-04-09T18:08:45Z",
        "updatedAt" : "2020-04-10T10:34:19Z",
        "lastEditedBy" : {
          "login" : "ckipp01",
          "name" : "Chris Kipp",
          "avatarUrl" : "https://avatars0.githubusercontent.com/u/13974112?u=7b6a2ddab8eec6f99e4e40ae9b81f71cb5ba92e5&v=4"
        },
        "tags" : [
        ]
      },
      {
        "id" : "f83ab067-10e6-4e28-8097-15ddb7dc98c8",
        "parentId" : "f5257cc2-2a1b-4741-9b01-f8e4ea31d47f",
        "author" : {
          "login" : "tgodzik",
          "name" : "Tomasz Godzik",
          "avatarUrl" : "https://avatars0.githubusercontent.com/u/3807253?u=094831e6a696f583ddfd86d3e5923fd8545c543a&v=4"
        },
        "body" : "Added a mention, good idea!",
        "createdAt" : "2020-04-10T10:03:33Z",
        "updatedAt" : "2020-04-10T10:34:19Z",
        "lastEditedBy" : {
          "login" : "tgodzik",
          "name" : "Tomasz Godzik",
          "avatarUrl" : "https://avatars0.githubusercontent.com/u/3807253?u=094831e6a696f583ddfd86d3e5923fd8545c543a&v=4"
        },
        "tags" : [
        ]
      }
    ],
    "commit" : "98216b111b90200af63cab4201335bfed979a303",
    "line" : 68,
    "diffHunk" : "@@ -1,1 +66,70 @@the `metals.superMethodLensesEnabled` configuration option - they are enabled by\ndefault. For example in Visual Studio Code:\n\n![Screenshot 2020-03-09 at 16 24 21](https://user-images.githubusercontent.com/10478402/76293133-cbbabb00-62b0-11ea-84be-06c992af768b.png)\n"
  }
]