[
  {
    "id" : "5e91969d-8d82-49e1-a3a6-95caee337fa0",
    "prId" : 799,
    "comments" : [
      {
        "id" : "07d3745c-f28e-435b-a40f-372097093b56",
        "parentId" : null,
        "author" : {
          "login" : "gabro",
          "name" : "Gabriele Petronella",
          "avatarUrl" : "https://avatars0.githubusercontent.com/u/691940?u=5aaf176f5da60764f857b8f8c6842217f737627f&v=4"
        },
        "body" : "good call, at least we have a single place where to change this.",
        "createdAt" : "2019-06-28T13:38:26Z",
        "updatedAt" : "2019-06-28T13:38:26Z",
        "lastEditedBy" : {
          "login" : "gabro",
          "name" : "Gabriele Petronella",
          "avatarUrl" : "https://avatars0.githubusercontent.com/u/691940?u=5aaf176f5da60764f857b8f8c6842217f737627f&v=4"
        },
        "tags" : [
        ]
      }
    ],
    "commit" : "fc72d8ead705e3c3076f10be4590a0a14f122d54",
    "line" : 5,
    "diffHunk" : "@@ -1,1 +51,55 @@  private def dialect(path: AbsolutePath): Option[Dialect] = {\n    Option(PathIO.extension(path.toNIO)).collect {\n      case \"scala\" => dialects.Scala\n      case \"sbt\" => dialects.Sbt\n      case \"sc\" => dialects.Sbt"
  }
]