[
  {
    "id" : "4a9be526-8e03-43c2-850e-30af17bd2e46",
    "prId" : 427,
    "comments" : [
      {
        "id" : "54ad57a2-9f9f-4fba-9f38-9b8a5debc100",
        "parentId" : null,
        "author" : {
          "login" : "gabro",
          "name" : "Gabriele Petronella",
          "avatarUrl" : "https://avatars0.githubusercontent.com/u/691940?u=5aaf176f5da60764f857b8f8c6842217f737627f&v=4"
        },
        "body" : "the check is redundant",
        "createdAt" : "2018-12-18T22:35:55Z",
        "updatedAt" : "2018-12-19T15:27:54Z",
        "lastEditedBy" : {
          "login" : "gabro",
          "name" : "Gabriele Petronella",
          "avatarUrl" : "https://avatars0.githubusercontent.com/u/691940?u=5aaf176f5da60764f857b8f8c6842217f737627f&v=4"
        },
        "tags" : [
        ]
      }
    ],
    "commit" : "0fd2367581ea78fe416c15f14ea826d3ce3ff35b",
    "line" : 83,
    "diffHunk" : "@@ -1,1 +50,54 @@    val paths = new util.ArrayList[Path]()\n    buildTargets.sourceDirectories.foreach { dir =>\n      if (!dir.isDirectory) {\n        dir.createDirectories()\n      }"
  },
  {
    "id" : "9d5e76ac-b965-4daf-a288-14733561a7ab",
    "prId" : 427,
    "comments" : [
      {
        "id" : "d7bff1ad-2f61-4ce4-80cb-05c9f2659619",
        "parentId" : null,
        "author" : {
          "login" : "laughedelic",
          "name" : "Alexey Alekhin",
          "avatarUrl" : "https://avatars2.githubusercontent.com/u/766656?v=4"
        },
        "body" : "👍 ",
        "createdAt" : "2018-12-19T01:12:49Z",
        "updatedAt" : "2018-12-19T15:27:54Z",
        "lastEditedBy" : {
          "login" : "laughedelic",
          "name" : "Alexey Alekhin",
          "avatarUrl" : "https://avatars2.githubusercontent.com/u/766656?v=4"
        },
        "tags" : [
        ]
      }
    ],
    "commit" : "0fd2367581ea78fe416c15f14ea826d3ce3ff35b",
    "line" : 35,
    "diffHunk" : "@@ -1,1 +24,28 @@ * Given we rely on file watching for critical functionality like Goto Definition and it's\n * really difficult to reproduce/investigate file watching issues, I think it's best to\n * have a single file watching solution that we have control over.\n *\n * This class does not watch for changes in `*.sbt` files in the workspace directory and"
  },
  {
    "id" : "f338cbba-8a03-4d8a-83b8-55e3c884284f",
    "prId" : 337,
    "comments" : [
      {
        "id" : "99eb50d0-d41b-414b-a9c5-00ada161699d",
        "parentId" : null,
        "author" : {
          "login" : "gabro",
          "name" : "Gabriele Petronella",
          "avatarUrl" : "https://avatars0.githubusercontent.com/u/691940?u=5aaf176f5da60764f857b8f8c6842217f737627f&v=4"
        },
        "body" : "what happens on Windows?",
        "createdAt" : "2018-11-24T13:11:11Z",
        "updatedAt" : "2018-11-27T10:23:41Z",
        "lastEditedBy" : {
          "login" : "gabro",
          "name" : "Gabriele Petronella",
          "avatarUrl" : "https://avatars0.githubusercontent.com/u/691940?u=5aaf176f5da60764f857b8f8c6842217f737627f&v=4"
        },
        "tags" : [
        ]
      },
      {
        "id" : "d405bb81-e98d-4126-abeb-00057c5d9d0c",
        "parentId" : "99eb50d0-d41b-414b-a9c5-00ada161699d",
        "author" : {
          "login" : "olafurpg",
          "name" : "Ólafur Páll Geirsson",
          "avatarUrl" : "https://avatars0.githubusercontent.com/u/1408093?v=4"
        },
        "body" : "BOOM 💥 (aka. not supported)\r\n\r\nAdded comment",
        "createdAt" : "2018-11-25T11:21:07Z",
        "updatedAt" : "2018-11-27T10:23:41Z",
        "lastEditedBy" : {
          "login" : "olafurpg",
          "name" : "Ólafur Páll Geirsson",
          "avatarUrl" : "https://avatars0.githubusercontent.com/u/1408093?v=4"
        },
        "tags" : [
        ]
      }
    ],
    "commit" : "8ab78d5883e2e77a843cca1ea641084e6e4a2875",
    "line" : 65,
    "diffHunk" : "@@ -1,1 +63,67 @@    }\n    val buildSbt = workspace.resolve(\"build.sbt\").toNIO\n    if (!Properties.isWin && Files.isRegularFile(buildSbt)) {\n      // Don't add individual files on Windows because it crashes.\n      paths.add(buildSbt)"
  }
]