[
  {
    "id" : "5ef47bb1-f79e-48ba-be06-94bd4e920797",
    "prId" : 2457,
    "prUrl" : "https://github.com/scalameta/metals/pull/2457",
    "prSource" : "GitHub",
    "comments" : [
      {
        "id" : "51d28756-5e27-4261-a049-4a47fc1f85e3",
        "parentId" : null,
        "author" : {
          "login" : "ckipp01",
          "name" : "Chris Kipp",
          "avatarUrl" : "https://avatars.githubusercontent.com/u/13974112?u=7b6a2ddab8eec6f99e4e40ae9b81f71cb5ba92e5&v=4"
        },
        "body" : "`autoFlush` here was `flushAlways`. There is a new asynchronous flush that wasn't available before, but I just stuck with what we had before and set flush to always.",
        "createdAt" : "2021-02-01T09:16:09Z",
        "updatedAt" : "2021-02-01T10:13:16Z",
        "lastEditedBy" : {
          "login" : "ckipp01",
          "name" : "Chris Kipp",
          "avatarUrl" : "https://avatars.githubusercontent.com/u/13974112?u=7b6a2ddab8eec6f99e4e40ae9b81f71cb5ba92e5&v=4"
        },
        "tags" : [
        ]
      }
    ],
    "commit" : "c554e4212897184ebcb0389966752b8b178eb0b0",
    "line" : 69,
    "diffHunk" : "@@ -1,1 +91,95 @@\n  def newFileWriter(logfile: AbsolutePath): FileWriter =\n    FileWriter(pathBuilder = PathBuilder.static(logfile.toNIO)).flushAlways\n\n  def defaultFormat: Formatter = formatter\"$date $levelPaddedRight $message\""
  }
]