[
  {
    "id" : "0dd0c0b0-a5cd-41e0-a875-31e204682c47",
    "prId" : 22,
    "comments" : [
      {
        "id" : "b8d82c4d-9905-489d-85be-1ec855e2babe",
        "parentId" : null,
        "author" : {
          "login" : "olafurpg",
          "name" : "Ólafur Páll Geirsson",
          "avatarUrl" : "https://avatars0.githubusercontent.com/u/1408093?v=4"
        },
        "body" : "I hadn't noticed this was implemented, we should use it instead of the buggy implementation I added on monday.",
        "createdAt" : "2017-11-09T18:40:56Z",
        "updatedAt" : "2017-11-09T18:47:55Z",
        "lastEditedBy" : {
          "login" : "olafurpg",
          "name" : "Ólafur Páll Geirsson",
          "avatarUrl" : "https://avatars0.githubusercontent.com/u/1408093?v=4"
        },
        "tags" : [
        ]
      },
      {
        "id" : "678d2f2c-8842-415d-a4e1-c95c47908498",
        "parentId" : "b8d82c4d-9905-489d-85be-1ec855e2babe",
        "author" : {
          "login" : "gabro",
          "name" : "Gabriele Petronella",
          "avatarUrl" : "https://avatars0.githubusercontent.com/u/691940?u=5aaf176f5da60764f857b8f8c6842217f737627f&v=4"
        },
        "body" : "Ah nice, it's the first time I notice it too!",
        "createdAt" : "2017-11-09T18:51:08Z",
        "updatedAt" : "2017-11-09T18:51:08Z",
        "lastEditedBy" : {
          "login" : "gabro",
          "name" : "Gabriele Petronella",
          "avatarUrl" : "https://avatars0.githubusercontent.com/u/691940?u=5aaf176f5da60764f857b8f8c6842217f737627f&v=4"
        },
        "tags" : [
        ]
      }
    ],
    "commit" : "f5a08cec9d466f68f9b683a3fae08d09b2b1025b",
    "line" : 58,
    "diffHunk" : "@@ -1,1 +56,60 @@   * Return the offset in the current document, for a given 0-based line/col position.\n   */\n  def positionToOffset(pos: Position): Int = {\n    val Position(line, col) = pos\n"
  }
]